README.md
setup.cfg
setup.py
cusfbamboo/__init__.py
cusfbamboo/circuit.py
cusfbamboo/engine.py
cusfbamboo/hx.py
cusfbamboo/isen.py
cusfbamboo/materials.py
cusfbamboo/plot.py
cusfbamboo/rao.py
cusfbamboo.egg-info/PKG-INFO
cusfbamboo.egg-info/SOURCES.txt
cusfbamboo.egg-info/dependency_links.txt
cusfbamboo.egg-info/requires.txt
cusfbamboo.egg-info/top_level.txt