Metadata-Version: 2.1
Name: cusfbamboo
Version: 0.2.4
Summary: Cooling system modelling for liquid rocket engines
Home-page: https://github.com/cuspaceflight/bamboo
Author: Daniel Gibbons
Author-email: daniel.u.gibbons@gmail.com
License: 	AGPL-3.0
Download-URL: https://github.com/cuspaceflight/bamboo/archive/refs/tags/0.2.4.tar.gz
Keywords: rocket,engine,liquid,cooling,spaceflight,thermal
Platform: UNKNOWN
Classifier: Development Status :: 4 - Beta
Classifier: Intended Audience :: Science/Research
Classifier: Topic :: Scientific/Engineering
Classifier: License :: OSI Approved :: GNU Affero General Public License v3
Classifier: Programming Language :: Python :: 3
